[
    {
        "id": 8101,
        "name": "wingstem",
        "image_url": null,
        "scientific_name": "Verbesina alternifolia 'Goldstrahl'",
        "family": "Asteraceae"
    },
    {
        "id": 8102,
        "name": "crown beard",
        "image_url": null,
        "scientific_name": "Verbesina helianthoides",
        "family": "Asteraceae"
    },
    {
        "id": 8103,
        "name": "great ironweed",
        "image_url": null,
        "scientific_name": "Vernonia arkansana",
        "family": "Asteraceae"
    },
    {
        "id": 8104,
        "name": "western ironweed",
        "image_url": null,
        "scientific_name": "Vernonia baldwinii",
        "family": "Asteraceae"
    },
    {
        "id": 8105,
        "name": "prairie ironweed",
        "image_url": null,
        "scientific_name": "Vernonia fasciculata",
        "family": "Asteraceae"
    },
    {
        "id": 8106,
        "name": "giant ironweed",
        "image_url": null,
        "scientific_name": "Vernonia gigantea",
        "family": "Asteraceae"
    },
    {
        "id": 8107,
        "name": "ironweed",
        "image_url": null,
        "scientific_name": "Vernonia lettermanii 'Iron Butterfly'",
        "family": "Asteraceae"
    },
    {
        "id": 8108,
        "name": "ironweed",
        "image_url": null,
        "scientific_name": "Vernonia missurica",
        "family": "Asteraceae"
    },
    {
        "id": 8109,
        "name": "New York ironweed",
        "image_url": null,
        "scientific_name": "Vernonia noveboracensis",
        "family": "Asteraceae"
    },
    {
        "id": 8110,
        "name": "ironweed",
        "image_url": null,
        "scientific_name": "Vernonia 'Southern Cross'",
        "family": "Asteraceae"
    },
    {
        "id": 8111,
        "name": "large speedwell",
        "image_url": null,
        "scientific_name": "Veronica austriaca",
        "family": "Plantaginaceae"
    },
    {
        "id": 8112,
        "name": "large speedwell",
        "image_url": null,
        "scientific_name": "Veronica austriaca subsp. teucrium 'Crater Lake Blue'",
        "family": "Plantaginaceae"
    },
    {
        "id": 8113,
        "name": "saw-leaved speedwell",
        "image_url": null,
        "scientific_name": "Veronica austriaca subsp. teucrium 'Royal Blue'",
        "family": "Plantaginaceae"
    },
    {
        "id": 8114,
        "name": "speedwell",
        "image_url": null,
        "scientific_name": "Veronica 'Blue Reflection'",
        "family": "Plantaginaceae"
    },
    {
        "id": 8115,
        "name": "ash-colored speedwell",
        "image_url": null,
        "scientific_name": "Veronica cinerea",
        "family": "Plantaginaceae"
    },
    {
        "id": 8116,
        "name": "speedwell",
        "image_url": null,
        "scientific_name": "Veronica 'Darwin's Blue'",
        "family": "Plantaginaceae"
    },
    {
        "id": 8117,
        "name": "speedwell",
        "image_url": null,
        "scientific_name": "Veronica 'Eveline'",
        "family": "Plantaginaceae"
    },
    {
        "id": 8118,
        "name": "speedwell",
        "image_url": null,
        "scientific_name": "Veronica 'First Love'",
        "family": "Plantaginaceae"
    },
    {
        "id": 8119,
        "name": "speedwell",
        "image_url": null,
        "scientific_name": "Veronica 'Foxy Lady'",
        "family": "Plantaginaceae"
    },
    {
        "id": 8120,
        "name": "Gentian speedwell",
        "image_url": null,
        "scientific_name": "Veronica gentianoides",
        "family": "Plantaginaceae"
    },
    {
        "id": 8121,
        "name": "Gentian speedwell",
        "image_url": null,
        "scientific_name": "Veronica gentianoides 'Alba'",
        "family": "Plantaginaceae"
    },
    {
        "id": 8122,
        "name": "Gentian speedwell",
        "image_url": null,
        "scientific_name": "Veronica gentianoides 'Variegata'",
        "family": "Plantaginaceae"
    },
    {
        "id": 8123,
        "name": "speedwell",
        "image_url": null,
        "scientific_name": "Veronica 'Giles van Hees'",
        "family": "Plantaginaceae"
    },
    {
        "id": 8124,
        "name": "speedwell",
        "image_url": null,
        "scientific_name": "Veronica 'Goodness Grows'",
        "family": "Plantaginaceae"
    },
    {
        "id": 8125,
        "name": "speedwell",
        "image_url": null,
        "scientific_name": "Veronica 'Heraud'",
        "family": "Plantaginaceae"
    },
    {
        "id": 8126,
        "name": "speedwell",
        "image_url": null,
        "scientific_name": "Veronica 'Hocus Pocus'",
        "family": "Plantaginaceae"
    },
    {
        "id": 8127,
        "name": "speedwell",
        "image_url": null,
        "scientific_name": "Veronica liwanensis",
        "family": "Plantaginaceae"
    },
    {
        "id": 8128,
        "name": "long leaf speedwell",
        "image_url": null,
        "scientific_name": "Veronica longifolia",
        "family": "Plantaginaceae"
    },
    {
        "id": 8129,
        "name": "long leaf speedwell",
        "image_url": null,
        "scientific_name": "Veronica longifolia 'Blauriesin' BLUE GIANTESS",
        "family": "Plantaginaceae"
    },
    {
        "id": 8130,
        "name": "long leaf speedwell",
        "image_url": null,
        "scientific_name": "Veronica longifolia 'Blue John'",
        "family": "Plantaginaceae"
    }
]