[
    {
        "id": 6931,
        "name": "grandiflora rose",
        "image_url": null,
        "scientific_name": "Rosa 'Wekisoblip' WILD BLUE YONDER",
        "family": "Rosaceae"
    },
    {
        "id": 6932,
        "name": "floribunda rose",
        "image_url": null,
        "scientific_name": "Rosa 'Wekpaltlez' HOT COCOA",
        "family": "Rosaceae"
    },
    {
        "id": 6933,
        "name": "floribunda rose",
        "image_url": null,
        "scientific_name": "Rosa 'Wekplapep' SCENTIMENTAL",
        "family": "Rosaceae"
    },
    {
        "id": 6934,
        "name": "floribunda rose",
        "image_url": null,
        "scientific_name": "Rosa 'Wekplapic' BETTY BOOP",
        "family": "Rosaceae"
    },
    {
        "id": 6935,
        "name": "large-flowered climbing rose",
        "image_url": null,
        "scientific_name": "Rosa 'Wekroalt' FOURTH OF JULY",
        "family": "Rosaceae"
    },
    {
        "id": 6936,
        "name": "large-flowered climbing rose",
        "image_url": null,
        "scientific_name": "Rosa WHITE DAWN",
        "family": "Rosaceae"
    },
    {
        "id": 6937,
        "name": "kordesii rose",
        "image_url": null,
        "scientific_name": "Rosa 'William Baffin'",
        "family": "Rosaceae"
    },
    {
        "id": 6938,
        "name": "Manchu rose",
        "image_url": null,
        "scientific_name": "Rosa xanthina",
        "family": "Rosaceae"
    },
    {
        "id": 6939,
        "name": "bourbon rose",
        "image_url": null,
        "scientific_name": "Rosa 'Z\u00e9phirine Drouhin'",
        "family": "Rosaceae"
    },
    {
        "id": 6940,
        "name": "shrub rose",
        "image_url": null,
        "scientific_name": "Rosa 'ZLEMarianne Yoshida' OSO EASY HAPPY PETIT PINK",
        "family": "Rosaceae"
    },
    {
        "id": 6941,
        "name": "landscape shrub rose",
        "image_url": null,
        "scientific_name": "Rosa 'Zlemartincipar' CANDY OH! VIVID RED",
        "family": "Rosaceae"
    },
    {
        "id": 6942,
        "name": "rose",
        "image_url": null,
        "scientific_name": "Rosa 'Zlesak Poly3' OSO HAPPY SMOOTHIE",
        "family": "Rosaceae"
    },
    {
        "id": 6943,
        "name": "eared roscoea",
        "image_url": null,
        "scientific_name": "Roscoea auriculata",
        "family": "Zingiberaceae"
    },
    {
        "id": 6944,
        "name": "roscoea",
        "image_url": null,
        "scientific_name": "Roscoea auriculata 'Beesiana'",
        "family": "Zingiberaceae"
    },
    {
        "id": 6945,
        "name": "roscoea",
        "image_url": null,
        "scientific_name": "Roscoea cautleyoides",
        "family": "Zingiberaceae"
    },
    {
        "id": 6946,
        "name": "roscoea",
        "image_url": null,
        "scientific_name": "Roscoea humeana",
        "family": "Zingiberaceae"
    },
    {
        "id": 6947,
        "name": "weeping buddleja",
        "image_url": null,
        "scientific_name": "Rostrinucula dependens",
        "family": "Lamiaceae"
    },
    {
        "id": 6948,
        "name": "rosularia",
        "image_url": null,
        "scientific_name": "Rosularia platyphylla",
        "family": "Crassulaceae"
    },
    {
        "id": 6949,
        "name": "butterfly bush",
        "image_url": null,
        "scientific_name": "Rotheca myricoides 'Ugandense'",
        "family": "Lamiaceae"
    },
    {
        "id": 6950,
        "name": "blackberry",
        "image_url": null,
        "scientific_name": "Rubus 'APF-190T' PRIME-ARK TRAVELER",
        "family": "Rosaceae"
    },
    {
        "id": 6951,
        "name": "blackberry",
        "image_url": null,
        "scientific_name": "Rubus 'APF-236T' BUSHEL AND BERRY BABY CAKES",
        "family": "Rosaceae"
    },
    {
        "id": 6952,
        "name": "raspberry",
        "image_url": null,
        "scientific_name": "Rubus biflorus",
        "family": "Rosaceae"
    },
    {
        "id": 6953,
        "name": "raspberry",
        "image_url": null,
        "scientific_name": "Rubus 'Bristol'",
        "family": "Rosaceae"
    },
    {
        "id": 6954,
        "name": "blackberry",
        "image_url": null,
        "scientific_name": "Rubus fruticosus 'Chester'",
        "family": "Rosaceae"
    },
    {
        "id": 6955,
        "name": "rubus",
        "image_url": null,
        "scientific_name": "Rubus henryi var. bambusarum",
        "family": "Rosaceae"
    },
    {
        "id": 6956,
        "name": "raspberry",
        "image_url": null,
        "scientific_name": "Rubus idaeus",
        "family": "Rosaceae"
    },
    {
        "id": 6957,
        "name": "raspberry",
        "image_url": null,
        "scientific_name": "Rubus idaeus 'Aureus'",
        "family": "Rosaceae"
    },
    {
        "id": 6958,
        "name": "raspberry",
        "image_url": null,
        "scientific_name": "Rubus idaeus 'Double Gold'",
        "family": "Rosaceae"
    },
    {
        "id": 6959,
        "name": "raspberry",
        "image_url": null,
        "scientific_name": "Rubus idaeus 'Fallgold'",
        "family": "Rosaceae"
    },
    {
        "id": 6960,
        "name": "red raspberry",
        "image_url": null,
        "scientific_name": "Rubus idaeus 'Heritage'",
        "family": "Rosaceae"
    }
]