[
    {
        "id": 7231,
        "name": "pincushion flower",
        "image_url": null,
        "scientific_name": "Scabiosa 'Fama White'",
        "family": "Caprifoliaceae"
    },
    {
        "id": 7232,
        "name": "pincushion flower",
        "image_url": null,
        "scientific_name": "Scabiosa 'Giant Blue'",
        "family": "Caprifoliaceae"
    },
    {
        "id": 7233,
        "name": "pincushion flower",
        "image_url": null,
        "scientific_name": "Scabiosa 'Grand Stone'",
        "family": "Caprifoliaceae"
    },
    {
        "id": 7234,
        "name": "pincushion flower",
        "image_url": null,
        "scientific_name": "Scabiosa japonica 'Blue Diamonds'",
        "family": "Caprifoliaceae"
    },
    {
        "id": 7235,
        "name": "pincushion flower",
        "image_url": null,
        "scientific_name": "Scabiosa 'Pink Mist'",
        "family": "Caprifoliaceae"
    },
    {
        "id": 7236,
        "name": "pincushion flower",
        "image_url": null,
        "scientific_name": "Scabiosa superba 'Mongolian Mist'",
        "family": "Caprifoliaceae"
    },
    {
        "id": 7237,
        "name": "pincushion flower",
        "image_url": null,
        "scientific_name": "Scabiosa 'Ultra Violet'",
        "family": "Caprifoliaceae"
    },
    {
        "id": 7238,
        "name": "pincushion flower",
        "image_url": null,
        "scientific_name": "Scabiosa 'Vivid Violet'",
        "family": "Caprifoliaceae"
    },
    {
        "id": 7239,
        "name": "African blood lily",
        "image_url": null,
        "scientific_name": "Scadoxus multiflorus",
        "family": "Amaryllidaceae"
    },
    {
        "id": 7240,
        "name": "fan flower",
        "image_url": null,
        "scientific_name": "Scaevola aemula",
        "family": "Goodeniaceae"
    },
    {
        "id": 7241,
        "name": "fan flower",
        "image_url": null,
        "scientific_name": "Scaevola aemula 'Blue Wonder'",
        "family": "Goodeniaceae"
    },
    {
        "id": 7242,
        "name": "beach naupaka",
        "image_url": null,
        "scientific_name": "Scaevola taccada",
        "family": "Goodeniaceae"
    },
    {
        "id": 7243,
        "name": "schavleria",
        "image_url": null,
        "scientific_name": "Schaueria flavicoma",
        "family": "Acanthaceae"
    },
    {
        "id": 7244,
        "name": "octopus tree",
        "image_url": null,
        "scientific_name": "Schefflera actinophylla",
        "family": "Araliaceae"
    },
    {
        "id": 7245,
        "name": "umbrella plant",
        "image_url": null,
        "scientific_name": "Schefflera arboricola",
        "family": "Araliaceae"
    },
    {
        "id": 7246,
        "name": "Brazilian peppertree",
        "image_url": null,
        "scientific_name": "Schinus terebinthifolius",
        "family": "Anacardiaceae"
    },
    {
        "id": 7247,
        "name": "schisandra",
        "image_url": null,
        "scientific_name": "Schisandra rubriflora",
        "family": "Schisandraceae"
    },
    {
        "id": 7248,
        "name": "little bluestem",
        "image_url": null,
        "scientific_name": "Schizachyrium scoparium",
        "family": "Poaceae"
    },
    {
        "id": 7249,
        "name": "little bluestem",
        "image_url": null,
        "scientific_name": "Schizachyrium scoparium 'Blaze'",
        "family": "Poaceae"
    },
    {
        "id": 7250,
        "name": "little bluestem",
        "image_url": null,
        "scientific_name": "Schizachyrium scoparium 'Blue Paradise' PRAIRIE WINDS",
        "family": "Poaceae"
    },
    {
        "id": 7251,
        "name": "little bluestem",
        "image_url": null,
        "scientific_name": "Schizachyrium scoparium (Branson Blue Strain)",
        "family": "Poaceae"
    },
    {
        "id": 7252,
        "name": "little bluestem",
        "image_url": null,
        "scientific_name": "Schizachyrium scoparium 'Carousel'",
        "family": "Poaceae"
    },
    {
        "id": 7253,
        "name": "little bluestem",
        "image_url": null,
        "scientific_name": "Schizachyrium scoparium 'Glaucum'",
        "family": "Poaceae"
    },
    {
        "id": 7254,
        "name": "little bluestem",
        "image_url": null,
        "scientific_name": "Schizachyrium scoparium 'Jazz'",
        "family": "Poaceae"
    },
    {
        "id": 7255,
        "name": "little bluestem",
        "image_url": null,
        "scientific_name": "Schizachyrium scoparium 'MinnblueA' BLUE HEAVEN",
        "family": "Poaceae"
    },
    {
        "id": 7256,
        "name": "little bluestem",
        "image_url": null,
        "scientific_name": "Schizachyrium scoparium 'Prairie Blues'",
        "family": "Poaceae"
    },
    {
        "id": 7257,
        "name": "little bluestem",
        "image_url": null,
        "scientific_name": "Schizachyrium scoparium 'Prairie Munchkin'",
        "family": "Poaceae"
    },
    {
        "id": 7258,
        "name": "little bluestem",
        "image_url": null,
        "scientific_name": "Schizachyrium scoparium 'Standing Ovation'",
        "family": "Poaceae"
    },
    {
        "id": 7259,
        "name": "little bluestem",
        "image_url": null,
        "scientific_name": "Schizachyrium scoparium 'The Blues'",
        "family": "Poaceae"
    },
    {
        "id": 7260,
        "name": "poor man's orchid",
        "image_url": null,
        "scientific_name": "Schizanthus pinnatus",
        "family": "Solanaceae"
    }
]